Workbook

Sheet DASHBOARD
B2: Overall # of Test Cases | C2: =SUM(C6,F6,I6) -> 1276
B4: PROGRESS TRACKER | C4: TOTAL SPRINT 1 | E4: PROGRESS TRACKER | F4: TOTAL SPRINT 2 | H4: PROGRESS TRACKER | I4: TOTAL SPRINT 3
B5: Status | E5: Status | H5: Status
B6: Total # of Test Case | C6: =SUM(C7:C11) -> 588 | E6: Total # of Test Case | F6: =SUM(F7:F11) -> 413 | H6: Total # of Test Case | I6: =SUM(I7:I11) -> 275
B7: Not Started | C7: =COUNTIF('Test Case - Sprint 1'!F:F,"NOT STARTED") -> 0 | E7: Not Started | F7: =COUNTIF('Test Case - Sprint 2'!F:F,"NOT STARTED") -> 25 | H7: Not Started | I7: =COUNTIF('Test Case - Sprint 3'!F:F,"NOT STARTED") -> 19
B8: Passed | C8: =COUNTIF('Test Case - Sprint 1'!F:F,"PASSED") -> 587 | E8: Passed | F8: =COUNTIF('Test Case - Sprint 2'!F:F,"PASSED") -> 388 | H8: Passed | I8: =COUNTIF('Test Case - Sprint 3'!F:F,"PASSED") -> 252
B9: Failed | C9: =COUNTIF('Test Case - Sprint 1'!F:F,"FAILED") -> 1 | E9: Failed | F9: =COUNTIF('Test Case - Sprint 2.0'!F:F,"FAILED") -> 0 | H9: Failed | I9: =COUNTIF('Test Case - Sprint 3'!F:F,"FAILED") -> 4
B10: Re-Test | C10: =COUNTIF('Test Case - Sprint 1'!F:F,"Re-Test") -> 0 | E10: Re-Test | F10: =COUNTIF('Test Case - Sprint 2.0'!F:F,"Re-Test") -> 0 | H10: Re-Test | I10: =COUNTIF('Test Case - Sprint 3'!F:F,"Re-Test") -> 0
B11: Blocked/Skip | C11: =COUNTIF('Test Case - Sprint 1'!F:F,"Blocked/Skip") -> 0 | E11: Blocked/Skip | F11: =COUNTIF('Test Case - Sprint 2'!F:F,"Blocked/Skip") -> 0 | H11: Blocked/Skip | I11: =COUNTIF('Test Case - Sprint 3'!F:F,"Blocked/Skip") -> 0
B13: Company | E13: Company | H13: Super Admin
B15: Sign Up | C15: =COUNTIF('Test Case - Sprint 1'!F5:F11,"Passed")/7 -> 1 | E15: Return Orders | H15: Login
B16: Verify Email | C16: =COUNTIF('Test Case - Sprint 1'!F13:F16,"Passed")/4 -> 1 | E16: Receipt Orders | H16: Dashboard
B17: Onboarding | C17: =COUNTIF('Test Case - Sprint 1'!F18:F42,"Passed")/25 -> 1 | E17: Purchase Orders | H17: Companies
B18: Log In | C18: =COUNTIF('Test Case - Sprint 1'!F44:F53,"Passed")/10 -> 1 | E18: Document Management | H18: Wedding Suppliers
B19: Forgot Password | C19: =COUNTIF('Test Case - Sprint 1'!F55:F61,"Passed")/7 -> 1 | E19: Campaign Management | H19: Media Library
B20: Reset Password | C20: =COUNTIF('Test Case - Sprint 1'!F63:F70,"Passed")/8 -> 1 | E20: Project Management | H20: Plans
B21: Profile Settings | C21: =COUNTIF('Test Case - Sprint 1'!F72:F82,"Passed")/11 -> 1 | E21: Calendar | H21: Plan Requests
B22: Dashboard | C22: =COUNTIF('Test Case - Sprint 1'!F84:F109,"Passed")/26 -> 1 | E22: Cases | H22: Plan Orders
B23: Staff - Users | C23: =COUNTIF('Test Case - Sprint 1'!F111:F132,"Passed")/23 -> 0.95652174 | E23: Meetings | H23: Coupons
B24: Staff - Roles | C24: =COUNTIF('Test Case - Sprint 1'!F134:F147,"Passed")/16 -> 0.875 | E24: Calls | H24: Currencies
B25: Lead Statuses | C25: =COUNTIF('Test Case - Sprint 1'!F149:F163,"Passed")/15 -> 1 | E25: Reports | H25: Referral Program
B26: Lead Sources | C26: =COUNTIF('Test Case - Sprint 1'!F165:F175,"Passed")/11 -> 1 | E26: Shipping Provider Types | H26: Landing Page
B27: Leads | C27: =COUNTIF('Test Case - Sprint 1'!F177:F205,"Passed")/30 -> 0.96666667 | E27: Plans | H27: Custom Pages
B28: Opportunity Stages | E28: Referral Program | H28: Contact Messages
B29: Opportunity Sources | E29: Media Library | H29: Newletters
B30: Opportunities | E30: Notification Templates | H30: Email Templates
B31: Account Type | E31: Settings | H31: Settings
B32: Account Industries
B33: Accounts
B34: Contacts
B35: Product Setup - Taxes
B36: Product Setup - Brands
B37: Product Setup - Categories
B38: Products
B39: Quotes
B40: Sales Orders
B41: Invoices
B42: Delivery Orders

Sheet Sheet4
A4: student
A6: Login | B6: Done | D6: =(E6+E7)/14 -> 0.57142857 | E6: =COUNTIF(B6:B19,"Done") -> 8
A7: Forgot password | B7: Done | E7: =COUNTIF(B6:B19,"Partial") -> 0
A8: Reset Password | B8: Done
A9: dashboard | B9: Status | C9: Real-time reflection of amount | D9: Progress bar of payment | E9: n/n months | F9: amount paid deduction
A10: tuition fees | B10: filtering | C10: search | D10: tables | E10: real time status
A11: other transaction
A12: terms and conditions | B12: Done
A13: finance policy | B13: Done | E13: =(D6+D23)/2 -> 0.42857143
A14: FAQ | B14: Done
A15: contact us
A16: header | B16: Done
A17: notification | B17: notifs
A18: Profile Management | B18: Done
A19: pay now | B19: list of banks | C19: upload payment where?
A21: admin
A23: Login | B23: Done | D23: =(E23+E24)/14 -> 0.28571429 | E23: =COUNTIF(B23:B36,"Done") -> 4
A24: Forgot password | B24: Done | E24: =COUNTIF(B23:B35,"Partial") -> 0
A25: Reset Password | B25: Done
A26: dashboard | B26: cards status | C26: filter | D26: status OR | E26: remove history logs?
A27: student management | B27: import csv | C27: search | D27: filter | E27: data tables
A28: payment management | B28: search | C28: filter | D28: data tables
A29: manage OR request | B29: search | C29: filter | D29: OR history
A30: staff management | B30: search | C30: filter | D30: edit access
A31: content management
A32: report management | B32: filter | C32: report csv | D32: status paid or np
A33: profile settings
A34: history logs | B34: activity | C34: data tables | D34: search | E34: filter
A35: header | B35: Done
A36: notification | B36: notifs
A37: view details | B37: PH | C37: MP | D37: view attachment | E37: status

Sheet Test Data Copy
A1: STUDENT | C1: ADMIN
A3: LOGIN | C3: LOGIN
A4: STUDENT ID | B4: alphanumeric which consist of 10 characters | C4: USERNAME
A5: PASSWORD | B5: Minimum of 8 alphanumeric character | C5: PASSWORD | D5: Minimum of 8 alphanumeric character
B6: Maximum of 50 alphanumeric character | D6: Maximum of 50 alphanumeric character
B7: Must have at least one special character | D7: Must have at least one special character
A8: FORGOT PASSWORD | C8: STAFF MANAGEMENT>ADD NEW STAFF
A9: EMAIL ADDRESS | B9: email add | C9: Profile image | D9: jpeg, png; up to 20mb
C10: FIRST NAME | D10: Maximum of 70 characters
A11: PAY | C11: MIDLE NAME | D11: OPTIONAL
A12: UPLOAD PROOF OF PAYMENT | C12: LAST NAME | D12: Maximum of 70 characters
C13: ACCOUNT
C14: ROLE
A15: PAY>MODE OF PAYMENT> CREDIT CARDS> CARD INFORMATION | C15: EMAIL ADDRESS | D15: Maximum of 70 characters
A16: CARD NUMBER | C16: MOBILE NUMBER | D16: Use the 11-digit (e.g. 09171234567) or 12-digit (e.g. 639181234567) format
A17: CARD NAME | C17: HOME ADDRESS | D17: Up to 70 characters
A18: EXPIRY DATE
A19: CVV | C19: STUDENT MANAGEMENT
C20: PAYMENT TRANSACTION
A21: CONTACT US | C21: STAFF MANAGEMENT
A22: NAME | C22: CONTENT MANAGEMENT
A23: STUDENT ID | C23: REPORTS MANAGEMENT
A24: EMAIL ADDRESS
A25: DEPARTMENT | C25: CHANGE PASSWORD
A26: MESSAGE | C26: Current password | D26: current password
C27: new password | D27: Minimum of 8 alphanumeric character
A28: PROFILE SETTINGS | D28: Maximum of 50 alphanumeric character
A29: Upload a Photo | B29: jpeg, png; up to 20mb | D29: Must have at least one special character
A30: Student ID | B30: alphanumeric which consist of 32 characters | C30: confirm password | D30: Minimum of 8 alphanumeric character
A31: Email address | B31: EMAIL | D31: Maximum of 50 alphanumeric character
A32: First name | B32: Maximum of 70 characters | D32: Must have at least one special character
A33: midle name | B33: OPTIONAL
A34: Last name | B34: Maximum of 70 characters | C34: Edit Student Balance
A35: mobile number | B35: Use the 11-digit (e.g. 09171234567) or 12-digit (e.g. 639181234567) format | C35: Current Balance
A36: birthday | B36: DATE PICKET MM/DD/YYYY | C36: payment status
A37: age | C37: enter reason for editing
A38: gender
A39: home address | C39: Add new FAQ Record
A40: course | B40: Pre input | C40: Question
A41: department | B41: Pre input | C41: Answer
A42: academic year | B42: Pre input
A43: semester | C43: Terms and condition
C44: title
A45: CHANGE PASSWORD | C45: body
A46: Current password | B46: current password
A47: new password | B47: Minimum of 8 alphanumeric character | C47: Contact us details
B48: Maximum of 50 alphanumeric character | C48: Phone number
B49: Must have at least one special character | C49: email address
A50: confirm password | B50: Minimum of 8 alphanumeric character | C50: shcool address
B51: Maximum of 50 alphanumeric character
B52: Must have at least one special character | C52: PAYMENT STATUS STUDENT
C53: paid
A54: Forgot password | C54: payment validated
A55: email
C56: PAYMENT STATUS STUDENT

Sheet Test Data
A1: COMPANY | B1: 1 | C1: 2 | D1: 3 | E1: 4 | F1: 5 | G1: 6 | H1: 7 | I1: 8 | J1: 9 | K1: 10
A24: SUPER ADMIN

Sheet Test Case - Sprint 1
A2: ITEM NO. | B2: TEST CASE / SCENARIO | C2: TEST STEP | D2: EXPECTED RESULT | E2: ACTUAL RESULT (1st RUN) | F2: STATUS | G2: TEST EVIDENCE (1st Run) | H2: COMMENT / REMARK
A3: Company
A4: Sign Up
A5: 1 | B5: Registration page loads | C5: 1. Navigate to Registration page | D5: Registration form loads successfully | F5: Passed
A6: 2 | B6: Successful registration | C6: 1. Enter valid Email 2. Enter Password 3. Enter Confirm Password 4. Check Agree to Terms and Conditions 5. Click Register | D6: User account is created and verification email is sent | F6: Passed
A7: 3 | B7: Password mismatch validation | C7: 1. Enter Password 2. Enter different Confirm Password 3. Click Register | D7: System displays password mismatch validation message | F7: Passed
A8: 4 | B8: Required fields validation | C8: 1. Leave required fields empty 2. Click Register | D8: System displays required field validation messages | F8: Passed
A9: 5 | B9: Terms and conditions required | C9: 1. Fill all fields 2. Do NOT check Agree to Terms 3. Click Register | D9: System prevents registration and prompts user to agree to terms | F9: Passed
A10: 6 | B10: Duplicate email registration | C10: 1. Register using an already existing email | D10: System prevents duplicate registration and displays error message | F10: Passed
A11: 7 | B11: Register with invalid email format | C11: 1. Enter test@example 2. Enter and Confirm password 3.Sign Up | D11: Validation error shown; registration blocked | E11: Accepts email format with no domain extension (e.g. test@example) | F11: Passed | H11: (PASSED) - 03/19/2026
A12: Verify Email
A13: 1 | B13: Verification email received | C13: 1. Register account 2. Check email inbox | D13: Verification email is received successfully | F13: Passed
A14: 2 | B14: Redirect to onboarding after successful email verification | C14: 1. Register a new account 2. Open verification email 3. Click verification link | D14: Email is verified and user is redirected to the onboarding page | F14: Passed
A15: 3 | B15: Invalid verification link | C15: 1. Click expired or modified verification link | D15: System displays invalid or expired link error | F15: Passed
A16: 4 | B16: Login without verification | C16: 1. Attempt to login before verifying email | D16: System restricts login and redirects to verify email page | F16: Passed
A17: Onboarding
A18: 1 | B18: Onboarding page loads successfully | C18: 1. Complete email verification | D18: Onboarding page loads displaying the Company Name setup step | F18: Passed
A19: 2 | B19: Prevent access to dashboard before onboarding completion | C19: 1. Verify email 2. Attempt to directly access dashboard URL | D19: System redirects user to onboarding until setup is completed | F19: Passed
A20: 3 | B20: Onboarding starts with company setup | C20: 1. Verify email 2. Observe first onboarding step | D20: System displays Enter Company Name as the first onboarding step | F20: Passed
A21: 4 | B21: Onboarding session persistence | C21: 1. Verify email 2. Start onboarding 3. Refresh page | D21: Onboarding progress remains and user stays on the same onboarding step | F21: Passed
A22: 5 | B22: Company name entry | C22: 1. Enter Company Name 2. Click Continue | D22: Company name is saved and onboarding proceeds to next step | F22: Passed
A23: 6 | B23: Empty company name validation | C23: 1. Leave Company Name empty 2. Click Continue | D23: System shows required field validation | F23: Passed
A24: 7 | B24: Default roles displayed | C24: 1. Navigate to Roles step | D24: Predefined roles Admin and Sales Manager are displayed | F24: Passed
A25: 8 | B25: Create custom role | C25: 1. Click Create Role 2. Enter Role Name 3. Select permissions 4. Save | D25: Custom role is created successfully | F25: Passed
A26: 9 | B26: Role permissions selection | C26: 1. Create role 2. Select permissions 3. Save | D26: Selected permissions are saved correctly | F26: Passed
A27: 10 | B27: Skip roles setup | C27: 1. Click Skip for Now | D27: System proceeds to next onboarding step | F27: Passed
A28: 11 | B28: Add team member | C28: 1. Enter Name 2. Enter Email 3. Select Role 4. Click Continue | D28: Team member is added successfully | F28: Passed
A29: 12 | B29: Role dropdown selection | C29: 1. Click Role dropdown | D29: Available roles are displayed for selection | F29: Passed
A30: 13 | B30: Invalid email validation | C30: 1. Enter invalid email format 2. Click Continue | D30: System displays email format validation error | E30: Accepts email format with no domain extension (e.g. test@example) | F30: Passed | H30: (PASSED) - 03/19/2026
A31: 14 | B31: Skip team member setup | C31: 1. Click Skip for Now | D31: System proceeds to dashboard | F31: Passed
A32: 15 | B32: Redirect to dashboard after onboarding | C32: 1. Complete onboarding process | D32: User is redirected to the dashboard successfully | F32: Passed
A33: 16 | B33: Dashboard loads correctly | C33: 1. Verify dashboard after onboarding | D33: Dashboard loads with company account initialized | F33: Passed
A34: 17 | B34: Plan subscription pop-up appears on first login | C34: 1. Login using newly registered company account 2. Navigate to Dashboard | D34: Plan subscription pop-up appears automatically on dashboard | F34: Passed
A35: 18 | B35: Display available plans in pop-up | C35: 1. Observe the plans displayed in the pop-up | D35: Available plans are displayed correctly with pricing and plan details | F35: Passed
A36: 19 | B36: Monthly / Yearly pricing toggle | C36: 1. Switch from Monthly to Yearly 2. Switch back to Monthly | D36: Plan pricing updates correctly based on selected billing cycle | F36: Passed
A37: 20 | B37: Subscribe to a plan from pop-up | C37: 1. Click Subscribe on a selected plan | D37: User proceeds to plan subscription or payment process | F37: Passed
A38: 21 | B38: Cancel / Close pop-up | C38: 1. Click Cancel / Close button | D38: Pop-up closes and dashboard remains accessible | F38: Passed
A39: 22 | B39: “Don’t show this again” checkbox functionality | C39: 1. Check Don’t show this again 2. Click Close 3. Refresh dashboard or login again | D39: Plan subscription pop-up no longer appears on dashboard | F39: Passed
A40: 23 | B40: Pop-up reappears when checkbox not selected | C40: 1. Close pop-up without checking Don’t show this again 2. Refresh dashboard or login again | D40: Pop-up appears again on dashboard | F40: Passed
A41: 24 | B41: Plan details correctness in pop-up | C41: 1. Compare plan name, price, and features shown in pop-up | D41: Plan information matches system plan configuration | F41: Passed
A42: 25 | B42: Toggle state persists while pop-up open | C42: 1. Select Yearly toggle 2. Browse plans within pop-up | D42: All displayed plans reflect selected billing cycle | F42: Passed
A43: Log In
A44: 1 | B44: Login page loads successfully | C44: 1. Click Login | D44: Login page loads with all required fields/buttons visible | F44: Passed
A45: 2 | B45: Login – valid credentials | C45: 1. Enter valid email 2. Enter valid password 3. Click Login | D45: User logs in successfully and is redirected to Dashboard | F45: Passed
A46: 3 | B46: Login using Enter key | C46: 1. Enter valid email & password 2. Press Enter | D46: Login is triggered and user is redirected | F46: Passed
A47: 4 | B47: Login with invalid email format | C47: 1. Enter test@ 2. Enter password 3. Login | D47: Validation error shown; login blocked | F47: Passed
A48: 5 | B48: Login – non-existing email | C48: 1. Enter email not in system 2. Any password 3. Login | D48: Error shown; user not logged in | F48: Passed
A49: 6 | B49: Login – blank email | C49: 1. Leave email empty 2. Enter password 3. Login | D49: Required validation appears; no login | F49: Passed
A50: 7 | B50: Login – invalid password | C50: 1. Enter valid email 2. Wrong password 3. Login | D50: Error shown; user not logged in | F50: Passed
A51: 8 | B51: Login – blank password | C51: 1. Enter email 2. Leave password empty 3. Login | D51: Required validation appears; no login | F51: Passed
A52: 9 | B52: Login – both fields blank | C52: 1. Leave email & password empty 2. Login | D52: Required validations shown | F52: Passed
A53: 10 | B53: Password masked by default | C53: 1. Type password | D53: Password characters are masked | F53: Passed
A54: Forgot Password
A55: 1 | B55: Forgot Password link visible | C55: 1. Observe login form | D55: “Forgot password?” link is visible and clickable | F55: Passed
A56: 2 | B56: Forgot Password page loads successfully | C56: 1. Click Forgot password? from Login | D56: Forgot Password page loads with Email field and submit button | F56: Passed
A57: 3 | B57: UI elements are displayed correctly | C57: 1. Observe page | D57: Email field, “Email password reset link” button, and “Back to login” link are visible | F57: Passed
A58: 4 | B58: Submit valid registered email | C58: 1. Enter registered email 2. Click Email password reset link | D58: Success message shown; reset email is sent | F58: Passed
A59: 5 | B59: Submit non-existing email | C59: 1. Enter unregistered email 2. Submit | D59: Generic success message shown | F59: Passed
A60: 6 | B60: Submit invalid email format | C60: 1. Enter test@ 2. Submit | D60: Validation error shown | F60: Passed
A61: 7 | B61: Submit empty email field | C61: 1. Leave email empty 2. Submit | D61: Required field validation shown | F61: Passed
A62: Reset Password
A63: 1 | B63: Password reset link opens reset password page | C63: 1. Click reset link from email | D63: User is redirected to Reset Password page | F63: Passed
A64: 2 | B64: UI elements visible | C64: 1. Observe page | D64: New Password, Confirm Password, Submit button visible | F64: Passed
A65: 3 | B65: Reset password with valid inputs | C65: 1. Enter valid new password 2. Enter matching confirm password 3. Click Reset/Submit | D65: Password is reset successfully; success message shown | F65: Passed
A66: 4 | B66: Login using newly reset password | C66: 1. Go to Login page 2. Enter email 3. Enter new password | D66: User logs in successfully | F66: Passed
A67: 5 | B67: Password confirmation mismatch | C67: 1. Enter new password 2. Enter different confirm password | D67: Validation error shown | F67: Passed
A68: 6 | B68: Empty password fields | C68: 1. Leave fields empty 2. Submit | D68: Required validation shown | F68: Passed
A69: 7 | B69: Reset link expires after defined time | C69: 1. Wait until link expiry 2. Click link | D69: Expired link error shown | F69: Passed
A70: 8 | B70: Reset link becomes invalid after use | C70: 1. Use reset link again after success | D70: Error shown; link no longer usable | F70: Passed
A71: Profile Settings
A72: 1 | B72: View profile settings | C72: 1. Click User Icon (Top Right) 2. Select Profile Settings | D72: Profile Settings page loads successfully | F72: Passed
A73: 2 | B73: Update profile information | C73: 1. Navigate to Profile Settings → Profile 2. Edit Name / Email / Company Name 3. Click Save | D73: Profile information updates successfully | F73: Passed
A74: 3 | B74: Upload profile avatar | C74: 1. Navigate to Profile Settings → Profile 2. Click Change Avatar 3. Upload valid image file 4. Save changes | D74: Avatar uploads and displays successfully | F74: Passed
A75: 4 | B75: Upload avatar with invalid file type | C75: 1. Click Change Avatar 2. Upload unsupported file type (e.g., PDF, DOCX) | D75: File selection does not show unsupported file types | F75: Passed
A76: 5 | B76: Upload avatar exceeding file size limit | C76: 1. Click Change Avatar 2. Upload image larger than 2MB | D76: System displays file size validation error | F76: Passed
A77: 6 | B77: Save profile with empty required fields | C77: 1. Clear Name or Email field 2. Click Save | D77: System prevents saving and shows validation message | F77: Passed
A78: 7 | B78: Update email address | C78: 1. Navigate to Profile Settings → Profile 2. Change Email Address 3. Click Save | D78: Email address updates successfully | F78: Passed
A79: 8 | B79: Change password successfully | C79: 1. Navigate to Profile Settings → Password 2. Enter Current Password 3. Enter New Password 4. Enter Confirm Password 5. Click Save Password | D79: Password updates successfully | F79: Passed
A80: 9 | B80: Incorrect current password | C80: 1. Enter incorrect Current Password 2. Enter new password 3. Click Save Password | D80: System displays error for incorrect current password | F80: Passed
A81: 10 | B81: Password mismatch validation | C81: 1. Enter New Password 2. Enter different Confirm Password 3. Click Save Password | D81: System shows password mismatch validation | F81: Passed
A82: 11 | B82: Empty password fields | C82: 1. Leave fields empty 2. Click Save Password | D82: System shows required field validation | F82: Passed
A83: Dashboard
A84: 1 | B84: Dashboard loads after successful login | C84: 1. Login with valid credentials | D84: User is redirected to Company Dashboard | F84: Passed
A85: 2 | B85: Dashboard URL access without login | C85: 1. Open /dashboard without session | D85: User redirected to Login page | F85: Passed
A86: 3 | B86: Company name displayed correctly | C86: 1. Observe top-right company name | D86: Logged-in company name is displayed correctly | F86: Passed
A87: 4 | B87: Language selector visible | C87: 1. Observe header | D87: Language dropdown is visible | F87: Passed
A88: 5 | B88: Language switch updates dashboard text | C88: 1. Change language | D88: All dashboard labels update correctly | F88: Passed
A89: 6 | B89: Language persists after refresh | C89: 1. Change language 2. Refresh page | D89: Selected language persists | F89: Passed
A90: 7 | B90: Refresh button reloads dashboard data | C90: 1. Click Refresh | D90: Dashboard widgets reload with updated data | F90: Passed
A91: 8 | B91: Total Employees widget displays correct count | C91: 1. Compare count with Staff list | D91: Employee count matches actual records | F91: Passed
A92: 9 | B92: Total Leads widget displays correct count | C92: 1. Compare with Leads module | D92: Lead count matches records | F92: Passed
A93: 10 | B93: Total Sales widget displays correct value | C93: 1. Compare with confirmed sales | D93: Sales count/value matches data | F93: Passed
A94: 11 | B94: Total Customers widget displays correct count | C94: 1. Compare with Accounts/Customers | D94: Customer count matches system data | F94: Passed
A95: 12 | B95: Total Projects widget displays correct count | C95: 1. Compare with Projects module | D95: Active projects count is accurate | F95: Passed
... A109: 26 | B109: Logout from dashboard | C109: 1. Logout 2. Try browser back | D109: User cannot reaccess dashboard | F109: Passed
A110: Staff - User
A111: 1 | B111: Users page loads | C111: 1. Go to Staff → Users | D111: Users list page loads without error | F111: Passed
A112: 2 | B112: Create User | C112: 1. Click Add User 2. Fill Name, Email, Password, Confirm Password, Role 3. Save | D112: User created and appears in list | F112: Passed
A113: 3 | B113: Create User – required field validations | C113: 1. Open Add User 2. Leave required fields empty 3. Click Save | D113: Required field errors displayed; no user created | F113: Passed
A114: 4 | B114: Create User – invalid email format | C114: 1. Enter email test@ 2. Fill others 3. Save | D114: Validation error; user not created | E114: Accepts email format with no domain extension (e.g. test@example) | F114: Passed | H114: (PASSED) - 03/19/2026
...

Sheet Test Case - Sprint 2
A2: ITEM NO. | B2: TEST CASE / SCENARIO | C2: TEST STEP | D2: EXPECTED RESULT | E2: ACTUAL RESULT (1st RUN) | F2: STATUS | G2: TEST EVIDENCE (1st Run) | H2: COMMENT / REMARK
A3: Company
A4: Return Orders
A5: 1 | B5: Return Orders page loads | C5: 1. Navigate to Return Orders module | D5: Return Orders list loads successfully | F5: Passed
A6: 2 | B6: Create Return Order – valid data (happy path) | C6: 1. Click Add Return Order 2. Enter Name 3. Select Sales Order 4. Enter Return Reason 5. Enter Return Date 6. Add Product 7. Click Save | D6: Return Order created successfully | F6: Passed
A7: 3 | B7: Name required validation | C7: 1. Leave Name empty 2. Click Save | D7: Validation error shown | F7: Passed
A8: 4 | B8: Sales Order required validation | C8: 1. Leave Sales Order empty 2. Click Save | D8: Validation error shown | F8: Passed
A9: 5 | B9: Selecting Sales Order auto-populates related fields | C9: 1. Click Add Return Order 2. Select existing Sales Order with products 3. Verify Account field 4. Verify Product & Services section | D9: Account and Contact match Sales Order; product lines available for selection | F9: Passed
A10: 6 | B10: Quantity validation – zero | C10: 1. Enter Quantity = 0 2. Save | D10: Validation error shown | F10: Passed
A11: 7 | B11: Quantity validation – negative | C11: 1. Enter Quantity = -1 2. Save | D11: Validation error shown | F11: Passed
A12: 8 | B12: Unit Price auto-filled | C12: 1. Select Product | D12: Unit Price auto-populated correctly | F12: Passed
A13: 9 | B13: Discount Type – Percentage | C13: 1. Select Discount Type = Percentage 2. Enter Discount Value | D13: Discount calculated correctly | F13: Passed
A14: 10 | B14: Discount Type – Fixed Amount | C14: 1. Select Discount Type = Fixed Amount 2. Enter Discount Value | D14: Discount calculated correctly | F14: Passed
A15: 11 | B15: Final Total calculation | C15: 1. Enter Quantity 2. Apply Discount | D15: Final Total calculated correctly | F15: Passed
A16: 12 | B16: Multiple product lines | C16: 1. Add multiple products 2. Save | D16: Totals calculated correctly | F16: Passed
... A28: 24 | B28: Pagination (10,25,50,100) | C28: 1. Select pagination options | D28: Messages display according to selected limit | F28: Passed
A29: Receipt Orders
A30: 1 | B30: Receipt Orders page loads | C30: 1. Navigate to Receipt Orders module | D30: Receipt Orders list loads successfully | F30: Passed
A31: 2 | B31: Create Receipt Order – valid data | C31: 1. Click Add Receipt Order 2. Enter Name 3. Enter Receipt Date 4. Select Purchase Order or Return Order 5. Add Product 6. Save | D31: Receipt Order created successfully | F31: Passed
A32: 3 | B32: Name required validation | C32: 1. Leave Name empty 2. Click Save | D32: Validation error shown | F32: Passed
A33: 4 | B33: Receipt Date required validation | C33: 1. Leave Receipt Date empty 2. Click Save | D33: Validation error shown | F33: Passed
A34: 5 | B34: Receipt Date before Expected Date | C34: 1. Enter Expected Date 2. Enter earlier Receipt Date 3. Save | D34: System handles consistently (allowed or validated per rule) | F34: Passed
A35: 6 | B35: Selecting Purchase Order auto-populates related fields | C35: 1. Click Add Receipt Order 2. Select existing Purchase Order 3. Verify Account 4. Verify Product lines | D35: Account and products match selected Purchase Order | F35: Passed
A36: 7 | B36: Selecting Return Order auto-populates related fields | C36: 1. Select existing Return Order 2. Verify Account and Product lines | D36: Account and products match selected Return Order | F36: Passed
A37: 8 | B37: Quantity validation – zero | C37: 1. Enter Quantity = 0 2. Save | D37: Validation error shown | F37: Passed
A38: 9 | B38: Quantity validation – negative | C38: 1. Enter Quantity = -1 2. Save | D38: Validation error shown | F38: Passed
A39: 10 | B39: Unit Price auto-filled | C39: 1. Select Product | D39: Unit Price auto-populated correctly | F39: Passed
A40: 11 | B40: Discount Type – Percentage | C40: 1. Select Percentage 2. Enter Discount Value | D40: Discount calculated correctly | F40: Passed
A41: 12 | B41: Discount Type – Fixed Amount | C41: 1. Select Fixed 2. Enter Discount Value | D41: Discount calculated correctly | F41: Passed
... A51: 22 | B51: Pagination (10,25,50,100) | C51: 1. Select pagination options | D51: Messages display according to selected limit | F51: Passed
A52: Purchase Orders
A53: 1 | B53: Purchase Orders page loads | C53: 1. Navigate to Purchase Orders module | D53: Purchase Orders list loads successfully | F53: Passed
A54: 2 | B54: Create Purchase Order – valid data | C54: 1. Click Add Purchase Order 2. Enter Name 3. Enter Order Date 4. Select Account 5. Add Product 6. Save | D54: Purchase Order created successfully | F54: Passed
A55: 3 | B55: Name required validation | C55: Name required validation | D55: Validation error shown | F55: Passed
A56: 4 | B56: Order Date required validation | C56: 1. Leave Order Date empty 2. Click Save | D56: Validation error shown | F56: Passed
A57: 5 | B57: Expected Delivery Date before Order Date | C57: 1. Enter Order Date 2. Enter earlier Expected Delivery Date 3. Save | D57: 1. Enter Order Date 2. Enter earlier Expected Delivery Date 3. Save | F57: Passed
A58: 6 | B58: Selecting Sales Order auto-populates related fields | C58: 1. Click Add Purchase Order 2. Select Sales Order 3. Verify Account and product data | D58: Account and products, and shipping provider match Sales Order | F58: Passed
A59: 7 | B59: Changing Sales Order resets product data | C59: 1. Select Sales Order A 2. Change to Sales Order B | D59: Product data updates accordingl | F59: Passed
A60: 8 | B60: Product data updates accordingl | C60: 1. Click Add under Product & Services 2. Select Product 3. Enter Quantity | D60: Product line added successfully | F60: Passed
A61: 9 | B61: Quantity validation – zero | C61: Quantity validation – zero | D61: 1. Enter Quantity = 0 2. Save | F61: Passed
A62: 10 | B62: Quantity validation – negative | C62: 1. Enter Quantity = -1 2. Save | D62: Validation error shown | F62: Passed
A63: 11 | B63: Unit Price auto-filled | C63: 1. Select Product | D63: Unit Price auto-populated correctly | F63: Passed
A64: 12 | B64: Discount Type – Percentage | C64: 1. Select Percentage 2. Enter Discount Value | D64: 1. Select Percentage 2. Enter Discount Value | F64: Passed
... A78: 26 | B78: Pagination (10,25,50,100) | C78: 1. Select pagination options | D78: Messages display according to selected limit | F78: Passed
A79: Document Management - Folders
A80: 1 | B80: Folders page loads | C80: 1. Navigate to Document Management → Folders | D80: Folders list loads successfully | F80: Passed
A81: 2 | B81: Create Folder | C81: 1. Click Add Folder 2. Enter Folder Name 3. Select Parent Folder (optional) 4. Enter Description (optional) 5. Set Status 6. Save | D81: Folder created and appears in list | F81: Passed
A82: 3 | B82: Folder Name required validation | C82: 1. Click Add Folder 2. Leave Folder Name empty 3. Save | D82: Validation error shown | F82: Passed
A83: 4 | B83: Create nested folder under Parent Folder | C83: 1. Create folder 2. Select Parent Folder ≠ Root 3. Save | D83: Folder created under selected parent | F83: Passed
A84: 5 | B84: Folder created under selected parent | C84: 1. Enter keyword in Search | D84: Matching folders displayed | F84: Passed
A85: 6 | B85: Matching folders displayed | C85: 1. Apply Parent Folder filter | D85: Only folders under parent shown | F85: Passed
A86: 7 | B86: Only folders under parent shown | C86: 1. Apply Status filter | D86: Correct results shown | F86: Passed
A87: 8 | B87: View Folder details | C87: 1. Open an existing Folder from list | D87: 1. Open an existing Folder from list | F87: Passed
A88: 9 | B88: Folder details displayed correctly | C88: 1. Edit fields 2. Save | D88: Changes saved successfully | F88: Passed
A89: 10 | B89: Change Folder status | C89: Change Folder status | D89: Status updates successfully according to selected value | F89: Passed
A90: 11 | B90: Delete Folder (empty) | C90: Delete Folder (empty) | D90: Folder deleted successfully | F90: Passed
A91: 12 | B91: Delete Folder with contents | C91: Delete Folder with contents | D91: System blocks delete or requires reassignment | E91: System allows deletion of Folder linked to a Document Record | F91: Passed | G91: (PASSED) 03/24/2026
A92: 13 | B92: Pagination (10,25,50,100) | C92: 1. Select pagination options | D92: Messages display according to selected limit | F92: Passed
A93: Document Management - Types
A94: 1 | B94: Types page loads | C94: 1. Navigate to Document Management → Types | D94: Types list loads successfully | F94: Passed
A95: 2 | B95: Create Document Type | C95: Type created and appears in list | D95: Type created and appears in list | F95: Passed
A96: 3 | B96: Type Name required validation | C96: 1. Click Add Type 2. Leave Type Name empty 3. Save | D96: 1. Click Add Type 2. Leave Type Name empty 3. Save | F96: Passed
A97: 4 | B97: Validation error shown | C97: Search Type | D97: 1. Enter keyword in Search | F97: Passed
A98: 5 | B98: Matching types displayed | C98: 1. Apply Status filter | D98: Correct results shown | F98: Passed
A99: 6 | B99: Correct results shown | C99: 1. Open an existing Type from list | D99: Type details displayed correctly | F99: Passed
A100: 7 | B100: Edit Type | C100: 1. Edit fields 2. Save | D100: Changes saved successfully | F100: Passed
A101: 8 | B101: Change Type status | C101: 1. Open existing Type 2. Change Status 3. Save | D101: Status updates successfully according to selected value | F101: Passed
A102: 9 | B102: Delete Type | C102: Delete Type | D102: Type deleted successfully | F102: Passed
A103: 10 | B103: Delete Type in use | C103: 1. Attempt delete Type used by documents | D103: System blocks deletion or requires reassignment | E103: System allows deletion of Type linked to a Document Record | F103: Passed | G103: (PASSED) 03/24/2026
A104: 11 | B104: Filter document types by Status | C104: 1. Navigate to Document Management → Types 2. Select Status (e.g., Active/Inactive) 3. Apply filter | D104: Only document types matching the selected status are displayed | F104: Passed
A105: 12 | B105: Pagination (10,25,50,100) | C105: 1. Select pagination options | D105: Messages display according to selected limit | F105: Passed
A106: Document Management -Documents
A107: 1 | B107: Documents page loads | C107: 1. Navigate to Document Management → Documents | D107: 1. Navigate to Document Management → Documents | F107: Passed
A108: 2 | B108: Documents list loads successfully | C108: 1. Click Add Document 2. Enter Document Name 3. Select Account/Folder/Type (optional per design) 4. Upload Attachment (if required by process) 5. Set Status 6. Save | D108: Document created and appears in list | F108: Passed
A109: 3 | B109: Document Name required validation | C109: 1. Click Add Document 2. Leave Document Name empty 3. Save | D109: Validation error shown | F109: Passed
A110: 4 | B110: Upload Attachment | C110: 1. Add Document 2. Upload a valid file 3. Save | D110: Attachment uploads successfully and is linked to document | F110: Passed
A111: 5 | B111: Invalid attachment | C111: Invalid attachment | D111: 1. Upload unsupported file type | F111: Passed
A112: 7 | B112: Expiration Date before Publish Date | C112: 1. Set Publish Date 2. Set Expiration Date earlier 3. Save | D112: Validation error or consistent handling | E112: System accepts documents with expiration date earlier than publish date | F112: Passed | G112: (PASSED) 03/24/2026
A113: 8 | B113: Assign To saved correctly | C113: 1. Select Assign To 2. Save | D113: Assignment persists | F113: Passed
A114: 9 | B114: View Document details | C114: 1. Open an existing Document from list | D114: Document details displayed correctly | F114: Passed
A115: 10 | B115: Edit Document | C115: 1. Edit fields 2. Save | D115: Changes saved successfully | F115: Passed
A116: 11 | B116: Change Document status | C116: 1. Open existing Document 2. Change Status 3. Save | D116: Status updates successfully according to selected value | F116: Passed
A117: 12 | B117: Delete Document | C117: 1. Delete document 2. Confirm | D117: Document deleted successfully | F117: Passed
A118: 13 | B118: Search Document | C118: 1. Enter keyword in Search | D118: Matching documents displayed | F118: Passed
A119: 14 | B119: Filter by Folder | C119: 1. Apply Folder filter | D119: Correct results shown | F119: Passed
A120: 15 | B120: Filter by Type | C120: 1. Apply Type filter | D120: Correct results shown | F120: Passed
A121: 16 | B121: Filter by Status | C121: 1. Apply Status filter | D121: Correct results shown | F121: Passed
A122: 17 | B122: Filter by Assigned To | C122: 1. Apply Assigned filter | D122: Correct results shown | F122: Passed
A123: 18 | B123: Filters persist across view change | C123: 1. Apply filters 2. Switch views | D123: Filters remain applied | F123: Passed
A124: 19 | B124: Change View (List/Grid) | C124: 1. Switch view from List to Grid (or vice versa) | D124: View changes successfully | F124: Passed
A125: 20 | B125: Pagination (10,25,50,100) | C125: 1. Select pagination options | D125: Messages display according to selected limit | F125: Passed
A126: Campaign Management - Campaign Types
A127: 1 | B127: Campaign Type page loads | C127: 1. Navigate to Campaign Management → Campaign Type | D127: Campaign Type list loads successfully | F127: Passed
A128: 2 | B128: Create Campaign Type | C128: 1. Click Add Campaign Type 2. Enter Name 3. (Optional) Enter Description and Color 4. Set Status 5. Save | D128: Campaign Type created and appears in list | F128: Passed
A129: 3 | B129: Search Campaign Type | C129: 1. Enter keyword in Search | D129: 1. Enter keyword in Search | F129: Passed
A130: 4 | B130: Filter Campaign Type by Status | C130: Filter Campaign Type by Status | D130: Correct results shown | F130: Passed
A131: 5 | B131: Correct results shown | C131: 1. Open an existing Campaign Type from list | D131: Details displayed correctly | F131: Passed
A132: 6 | B132: Edit Campaign Type | C132: Edit Campaign Type | D132: Changes saved successfully | F132: Passed
A133: 7 | B133: Change Campaign Type status | C133: 1. Open existing Campaign Type 2. Change Status 3. Save changes | D133: Status updates successfully according to selected value | F133: Passed
A134: 8 | B134: Delete Campaign Type (unused) | C134: 1. Delete Campaign Type not used in Campaigns | D134: 1. Delete Campaign Type not used in Campaigns | F134: Passed
...

Sheet Test Case - Sprint 2.0
A2: ITEM NO. | B2: TEST CASE / SCENARIO | C2: TEST STEP | D2: SEVERITY | E2: EXPECTED RESULT | F2: ACTUAL RESULT (1st RUN) | G2: STATUS | H2: TEST EVIDENCE (1st Run) | I2: COMMENT / REMARK
A3: STUDENT
A4: Notification
B5: Notifications | C5: 1. Click Bell icon 2. Click any Notification | E5: • User will be redirected to the notification (Tuition fees, Other transaction) | G5: NOT YET STARTED
A6: Other Transaction
B7: Menu - Dashboard - Overview | C7: 1. Click Dashboard Button | E7: • User will be redirected to Dashboards • User will be able to view the overview that consists of: - Profile Picture - Full name - Student ID - Academic Year - Year Level - Semester - Course - Department • User will be able to view Outstanding balance - Tooltip icon - outstanding balance (Hover Tooltip) - Progress bar & number of months - Amount Paid - Total - Pay button --------------------------------------------------- - Due on - Extended Due on | G7: NOT YET STARTED
B8: Menu - Dashboard - Recent Activity | C8: 1. Click Dashboard Button | E8: • User will be redirected to Dashboards • User will be able to view the Recent Activity that consists of: Latest Transactions - View All link - Details of Latest Transaction Official Receipt - View All link - Details of Latest Transaction - View Receeipt Link - Processing of OR must not be seen in this table | G8: NOT YET STARTED
B9: Menu - Tuition fees | C9: 1. Click Tuition Fees Button | E9: • User can be able to view - Pay outstanding balance - Search - Date Range - Filter by (Payment Status / OR status) Tuition Table - Reference No. - Date of payment - Payment Status - Amount - Official Receipt Status - Pagination | G9: NOT YET STARTED
B10: Support - Terms and Conditions | C10: 1. Click Terms and Conditions Button | E10: • User is able to view Terms and Conditions • User is able to view the Last Revised | G10: NOT YET STARTED
B11: Support - Finance Policy | C11: 1. Click Finance Policy Button | E11: • User is able to view Finance Policy • User is able to view the Last Revised | G11: NOT YET STARTED
B12: Support - FAQs | C12: 1. Click FAQs Button | E12: • User is able to view FAQs | G12: NOT YET STARTED
B13: Support - Contact us | C13: 1. Click Contact us Button | E13: • User is able to view Contact us -Send us an Email - Contact details | G13: NOT YET STARTED
A14: Terms & Conditions
B15: Menu - Dashboard - Overview | C15: 1. Click Dashboard Button | E15: • User will be redirected to Dashboards • User will be able to view the overview that consists of: - Profile Picture - Full name - Student ID - Academic Year - Year Level - Semester - Course - Department • User will be able to view Outstanding balance - Tooltip icon - outstanding balance (Hover Tooltip) - Progress bar & number of months - Amount Paid - Total - Pay button --------------------------------------------------- - Due on - Extended Due on | G15: NOT YET STARTED
B16: Menu - Dashboard - Recent Activity | C16: 1. Click Dashboard Button | E16: • User will be redirected to Dashboards • User will be able to view the Recent Activity that consists of: Latest Transactions - View All link - Details of Latest Transaction Official Receipt - View All link - Details of Latest Transaction - View Receeipt Link - Processing of OR must not be seen in this table | G16: NOT YET STARTED
B17: Menu - Tuition fees | C17: 1. Click Tuition Fees Button | E17: • User can be able to view - Pay outstanding balance - Search - Date Range - Filter by (Payment Status / OR status) Tuition Table - Reference No. - Date of payment - Payment Status - Amount - Official Receipt Status - Pagination | G17: NOT YET STARTED
B18: Menu - Other Transactions | C18: 1. Click Other Transaction Button | E18: • User can be able to view - Pay other fees - Search - Date Range Other Transaction Table - Reference No. - Date of payment - Payment Status - Miscellaneous item - Amount - Payment Channel - Pagination | G18: NOT YET STARTED
B19: Support - Finance Policy | C19: 1. Click Finance Policy Button | E19: • User is able to view Finance Policy • User is able to view the Last Revised | G19: NOT YET STARTED
B20: Support - FAQs | C20: 1. Click FAQs Button | E20: • User is able to view FAQs | G20: NOT YET STARTED
B21: Support - Contact us | C21: 1. Click Contact us Button | E21: • User is able to view Contact us -Send us an Email - Contact details | G21: NOT YET STARTED
B22: Terms and Condition | C22: 1. View Terms & Conditions | E22: • View Terms and Conditions Content | G22: NOT YET STARTED
B23: Terms and Condition - Last Revised | C23: 1. View Terms & Conditions | E23: • Last Revised must be updated when the Terms and Conditions is revised | G23: NOT YET STARTED
A24: Finance Policy
B25: Menu - Dashboard - Overview | C25: 1. Click Dashboard Button | E25: • User will be redirected to Dashboards • User will be able to view the overview that consists of: - Profile Picture - Full name - Student ID - Academic Year - Year Level - Semester - Course - Department • User will be able to view Outstanding balance - Tooltip icon - outstanding balance (Hover Tooltip) - Progress bar & number of months - Amount Paid - Total - Pay button --------------------------------------------------- - Due on - Extended Due on | G25: NOT YET STARTED
B26: Menu - Dashboard - Recent Activity | C26: 1. Click Dashboard Button | E26: • User will be redirected to Dashboards • User will be able to view the Recent Activity that consists of: Latest Transactions - View All link - Details of Latest Transaction Official Receipt - View All link - Details of Latest Transaction - View Receeipt Link - Processing of OR must not be seen in this table | G26: NOT YET STARTED
B27: Menu - Tuition fees | C27: 1. Click Tuition Fees Button | E27: • User can be able to view - Pay outstanding balance - Search - Date Range - Filter by (Payment Status / OR status) Tuition Table - Reference No. - Date of payment - Payment Status - Amount - Official Receipt Status - Pagination | G27: NOT YET STARTED
B28: Menu - Other Transactions | C28: 1. Click Other Transaction Button | E28: • User can be able to view - Pay other fees - Search - Date Range Other Transaction Table - Reference No. - Date of payment - Payment Status - Miscellaneous item - Amount - Payment Channel - Pagination | G28: NOT YET STARTED
B29: Support - Terms and Conditions | C29: 1. Click Terms and Conditions Button | E29: • User is able to view Terms and Conditions • User is able to view the Last Revised | G29: NOT YET STARTED
B30: Support - FAQs | C30: 1. Click FAQs Button | E30: • User is able to view FAQs | G30: NOT YET STARTED
B31: Support - Contact us | C31: 1. Click Contact us Button | E31: • User is able to view Contact us -Send us an Email - Contact details | G31: NOT YET STARTED
B32: Finance Policy | C32: 1. View Terms & Conditions | E32: • View Terms and Conditions Content | G32: NOT YET STARTED
B33: Finance Policy - Last Revised | C33: 1. View Terms & Conditions | E33: • Last Revised must be updated when the Terms and Conditions is revised | G33: NOT YET STARTED
A34: FAQs
B35: Menu - Dashboard - Overview | C35: 1. Click Dashboard Button | E35: • User will be redirected to Dashboards • User will be able to view the overview that consists of: - Profile Picture - Full name - Student ID - Academic Year - Year Level - Semester - Course - Department • User will be able to view Outstanding balance - Tooltip icon - outstanding balance (Hover Tooltip) - Progress bar & number of months - Amount Paid - Total - Pay button --------------------------------------------------- - Due on - Extended Due on | G35: NOT YET STARTED
B36: Menu - Dashboard - Recent Activity | C36: 1. Click Dashboard Button | E36: • User will be redirected to Dashboards • User will be able to view the Recent Activity that consists of: Latest Transactions - View All link - Details of Latest Transaction Official Receipt - View All link - Details of Latest Transaction - View Receeipt Link - Processing of OR must not be seen in this table | G36: NOT YET STARTED
B37: Menu - Tuition fees | C37: 1. Click Tuition Fees Button | E37: • User can be able to view - Pay outstanding balance - Search - Date Range - Filter by (Payment Status / OR status) Tuition Table - Reference No. - Date of payment - Payment Status - Amount - Official Receipt Status - Pagination | G37: NOT YET STARTED
B38: Menu - Other Transactions | C38: 1. Click Other Transaction Button | E38: • User can be able to view - Pay other fees - Search - Date Range Other Transaction Table - Reference No. - Date of payment - Payment Status - Miscellaneous item - Amount - Payment Channel - Pagination | G38: NOT YET STARTED
B39: Support - Terms and Conditions | C39: 1. Click Terms and Conditions Button | E39: • User is able to view Terms and Conditions • User is able to view the Last Revised | G39: NOT YET STARTED
B40: Support - Finance Policy | C40: 1. Click Finance Policy Button | E40: • User is able to view Finance Policy • User is able to view the Last Revised | G40: NOT YET STARTED
B41: Support - Contact us | C41: 1. Click Contact us Button | E41: • User is able to view Contact us -Send us an Email - Contact details | G41: NOT YET STARTED
B42: Search | C42: 1. Input Text in the Search Field | E42: • User will be able to see the matched FAQs based on the inputted text on search field | G42: NOT YET STARTED
B43: Plus Icon | C43: 1. Click Plus Icon | E43: FAQs Record will collapse the clicked Plus icon | G43: NOT YET STARTED
B44: Minus Icon | C44: 1. Click Minus Icon | E44: FAQs Record will uncollapse the clicked Minus icon | G44: NOT YET STARTED
A45: Contact Us
B46: Menu - Dashboard - Overview | C46: 1. Click Dashboard Button | E46: • User will be redirected to Dashboards • User will be able to view the overview that consists of: - Profile Picture - Full name - Student ID - Academic Year - Year Level - Semester - Course - Department • User will be able to view Outstanding balance - Tooltip icon - outstanding balance (Hover Tooltip) - Progress bar & number of months - Amount Paid - Total - Pay button --------------------------------------------------- - Due on - Extended Due on | G46: NOT YET STARTED
B47: Menu - Dashboard - Recent Activity | C47: 1. Click Dashboard Button | E47: • User will be redirected to Dashboards • User will be able to view the Recent Activity that consists of: Latest Transactions - View All link - Details of Latest Transaction Official Receipt - View All link - Details of Latest Transaction - View Receeipt Link - Processing of OR must not be seen in this table | G47: NOT YET STARTED
B48: Menu - Tuition fees | C48: 1. Click Tuition Fees Button | E48: • User can be able to view - Pay outstanding balance - Search - Date Range - Filter by (Payment Status / OR status) Tuition Table - Reference No. - Date of payment - Payment Status - Amount - Official Receipt Status - Pagination | G48: NOT YET STARTED
B49: Menu - Other Transactions | C49: 1. Click Other Transaction Button | E49: • User can be able to view - Pay other fees - Search - Date Range Other Transaction Table - Reference No. - Date of payment - Payment Status - Miscellaneous item - Amount - Payment Channel - Pagination | G49: NOT YET STARTED
B50: Support - Terms and Conditions | C50: 1. Click Terms and Conditions Button | E50: • User is able to view Terms and Conditions • User is able to view the Last Revised | G50: NOT YET STARTED
B51: Support - Finance Policy | C51: 1. Click Finance Policy Button | E51: • User is able to view Finance Policy • User is able to view the Last Revised | G51: NOT YET STARTED
B52: Support - FAQs | C52: 1. Click FAQs Button | E52: • User is able to view FAQs | G52: NOT YET STARTED
B53: Sending of Email - Subject | C53: 1. Input Subject (Required, Maximum 50 Characters) 2. Input Message (Required, Maximum of 255 Characters) | E53: • User is able to input aplanumeric characters • This field is Required to send email | G53: NOT YET STARTED
B54: Sending of Email - Message | C54: 1. Input Subject (Required, Maximum 50 Characters) 2. Input Message (Required, Maximum of 255 Characters) | E54: • User is able to input aplanumeric characters • This field is Required to send email | G54: NOT YET STARTED
B55: Sending of Email - Successful email | C55: 1. Input Subject (Required, Maximum 50 Characters) 2. Input Message (Required, Maximum of 255 Characters) 3. Click "Send Message" Button | E55: • Subject Field must have inputs • Message Field must have inputs • The receiving Email must receive the email | G55: NOT YET STARTED
B56: Sending of Email - Unuccessful email (Subject) | C56: 1. Input Subject (Required, Maximum 50 Characters) 2. Click "Send Message" Button | E56: • Error in Subject Field that message field is required • Sending Email must not proceed | G56: NOT YET STARTED
B57: Sending of Email - Unuccessful email (Message) | C57: 1. Input Message (Required, Maximum 225 Characters) 2. Click "Send Message" Button | E57: • Error in Message Field that message field is required • Sending Email must not proceed | G57: NOT YET STARTED
A58: ADMIN
A59: Notification
B60: Notifications | C60: 1. Click Bell icon 2. Click any Notification | E60: • User will be redirected to Payment Management Tab | G60: NOT YET STARTED
A61: Dashboard
A63: Student Management
A65: Payment Management
A67: Manage OR
A69: Staff Management
A71: Content Management
A73: Report Management
A75: Profile Settings
A77: History Logs

Sheet Test Case - Sprint 3
A2: ITEM NO. | B2: TEST CASE / SCENARIO | C2: TEST STEP | D2: EXPECTED RESULT | E2: ACTUAL RESULT (1st RUN) | F2: STATUS | G2: TEST EVIDENCE (1st Run) | H2: COMMENT / REMARK
A3: Super Admin
A4: Sign In
A5: 1 | B5: Login page loads successfully | C5: 1. Click Login | D5: Login page loads with all required fields/buttons visible | F5: Passed
A6: 2 | B6: Login – valid credentials | C6: 1. Enter valid email 2. Enter valid password 3. Click Login | D6: User logs in successfully and is redirected to Dashboard | F6: Passed
A7: 3 | B7: Login using Enter key | C7: 1. Enter valid email & password 2. Press Enter | D7: Login is triggered and user is redirected | F7: Passed
A8: 4 | B8: Login with invalid email format | C8: 1. Enter test@ 2. Enter password 3. Login | D8: Validation error shown; login blocked | F8: Passed
A9: 5 | B9: Login – non-existing email | C9: 1. Enter email not in system 2. Any password 3. Login | D9: Error shown; user not logged in | F9: Passed
A10: 6 | B10: Login – blank email | C10: 1. Leave email empty 2. Enter password 3. Login | D10: Required validation appears; no login | F10: Passed
A11: 7 | B11: Login – invalid password | C11: 1. Enter valid email 2. Wrong password 3. Login | D11: Error shown; user not logged in | F11: Passed
A12: 8 | B12: Login – blank password | C12: 1. Enter email 2. Leave password empty 3. Login | D12: Required validation appears; no login | F12: Passed
A13: 9 | B13: Login – both fields blank | C13: 1. Leave email & password empty 2. Login | D13: Required validations shown | F13: Passed
A14: 10 | B14: Password masked by default | C14: 1. Type password | D14: Password characters are masked | F14: Passed
A15: Dashboard
A16: 1 | B16: Dashboard page loads | C16: 1. Login as Super Admin 2. Navigate to Dashboard | D16: Dashboard loads successfully with all widgets displayed | F16: Passed
A17: 2 | B17: Total Company widget accuracy | C17: 1. Check Total Company count on Dashboard 2. Compare with Companies module count | D17: Total Company count matches actual number of companies | F17: Passed
A18: 3 | B18: Total Users widget accuracy | C18: 1. View Total Users widget 2. Compare with system users list | D18: Total Users value matches actual users in system | F18: Passed
A19: 4 | B19: Active Subscriptions display | C19: 1. View Active Subscriptions widget | D19: Correct number of active subscriptions displayed | F19: Passed
A20: 5 | B20: Monthly Growth chart display | C20: 1. Observe Monthly Growth chart | D20: Chart loads successfully and reflects system growth data | F20: Passed
A21: 6 | B21: Total Revenue widget accuracy | C21: 1. Check Total Revenue value 2. Compare with payment transactions | D21: Revenue value matches recorded payments | F21: Passed
A22: 7 | B22: Recent Activity feed | C22: 1. View Recent Activity section | D22: Recent system activities are displayed correctly | F22: Passed
A23: 8 | B23: Top Performing Plans display | C23: 1. View Top Performing Plans widget | D23: Plans ranked correctly based on subscriptions | F23: Passed
A24: 9 | B24: Payment Transaction Log display | C24: 1. View Payment Transaction Log section | D24: Recent payment transactions displayed correctly | F24: Passed
A25: 10 | B25: Company Management Explore button | C25: 1. Click Explore under Company Management | D25: System redirects to Companies module | F25: Not Started
A26: 11 | B26: Subscription Management Explore button | C26: 1. Click Explore under Subscription Management | D26: System redirects to Subscription Management module | F26: Not Started
A27: 12 | B27: Revenue Tracking Explore button | C27: 1. Click Explore under Revenue Tracking | D27: System redirects to Revenue Tracking module | F27: Not Started
A28: 13 | B28: System Growth Explore button | C28: 1. Click Explore under System Growth | D28: System redirects to System Growth module | F28: Not Started
A29: Companies
A30: 1 | B30: Companies page loads | C30: 1. Navigate to Companies module | D30: Companies page loads successfully | F30: Passed
A31: 2 | B31: Add company (valid data) | C31: 1. Click Add Company 2. Enter Company Name 3. Enter Email 4. Enable Login toggle 5. Enter Password 6. Save | D31: Company created successfully and appears in list | F31: Passed
A32: 3 | B32: Required field validation (Company Name) | C32: 1. Leave Company Name empty 2. Click Save | D32: System displays validation error | F32: Passed
A33: 4 | B33: Required field validation (Email) | C33: 1. Leave Email empty 2. Click Save | D33: System displays validation error | F33: Passed
A34: 5 | B34: Invalid email format validation | C34: 1. Enter invalid email format 2. Click Save | D34: System shows validation error | E34: Accepts email format with no domain extension (e.g. test@example) | F34: Passed | G34: (PASSED) 03/19/2026
A35: 6 | B35: Login toggle behavior | C35: 1. Enable Login toggle | D35: Password field becomes required | F35: Passed
A36: 7 | B36: Disable login toggle | C36: 1. Disable login toggle | D36: Password field becomes optional or hidden | F36: Passed
A37: 8 | B37: Switch to List View | C37: Click List View option | D37: Companies displayed in list format | F37: Passed
A38: 9 | B38: Switch to Grid View | C38: Click Grid View option | D38: Companies displayed in grid format | E38: UI Overflow on some companies with longer details | F38: Passed | G38: (PASSED) 03/24/2026
A39: 10 | B39: Grid view displays company details | C39: 1. Open Grid View | D39: Company cards display correct details (company name, email, status, etc.) | F39: Passed
A40: 11 | B40: Search company by name | C40: Enter company name in search | D40: Matching companies displayed | F40: Passed
A41: 12 | B41: Search company by email | C41: Enter company email | D41: Correct company displayed | F41: Passed
A42: 13 | B42: Search non-existing company | C42: Enter invalid keyword | D42: No results displayed | F42: Passed
A43: 14 | B43: Filter by Status | C43: Select Active/Inactive filter | D43: Companies filtered correctly | F43: Passed
A44: 15 | B44: Filter by Start Date | C44: Select start date filter | D44: Companies filtered by start date | F44: Passed
A45: 16 | B45: Filter by End Date | C45: Select end date filter | D45: Companies filtered by end date | F45: Passed
A46: 17 | B46: Search functionality in Grid View | C46: 1. Navigate to module 2. Select Grid View 3. Enter keyword in Search field | D46: Matching records are displayed in Grid View | F46: Passed
A47: 18 | B47: Search with no results | C47: 1. Enter non-existing keyword in Search | D47: System displays No results found message | F47: Passed
A48: 19 | B48: Clear search results | C48: 1. Enter keyword in Search 2. Clear search field | D48: Full list of records is displayed again | F48: Passed
A49: 20 | B49: Filter records in Grid View | C49: 1. Navigate to module 2. Select Grid View 3. Apply filter | D49: Records matching filter criteria are displayed | F49: Passed
A50: 21 | B50: Search and filter combination | C50: 1. Apply filter 2. Enter keyword in Search | D50: System displays records matching both search and filter criteria | F50: Passed
... A57: 28 | B57: User Logs Pagination 10/25/50/100 | C57: 1. Navigate to Companies module 2. Select pagination options 10, 25, 50, 100 sequentially 3. Observe displayed records | D57: System correctly updates displayed logs according to selected pagination | F57: Passed
A58: Wedding Suppliers
A59: 1 | B59: Wedding Suppliers page loads | C59: 1. Login as Super Admin 2. Navigate to Wedding Suppliers module | D59: Wedding Suppliers page loads successfully | F59: Passed
A60: 2 | B60: Add supplier with valid data | C60: 1. Click Add Supplier 2. Enter Name 3. Select Category 4. Enter supplier details 5. Click Save | D60: Supplier is successfully created and displayed in the list | F60: Passed
A61: 3 | B61: Required field validation – Name | C61: 1. Click Add Supplier 2. Leave Name empty 3. Click Save | D61: System displays validation error for Name field | F61: Passed
A62: 4 | B62: Required field validation – Category | C62: 1. Click Add Supplier 2. Leave Category empty 3. Click Save | D62: System displays validation error for Category | F62: Passed
A63: 5 | B63: Email format validation | C63: 1. Enter invalid email format 2. Save supplier | D63: System shows email validation error | E63: Accepts email format with no domain extension (e.g. test@example) | F63: Passed | G63: (PASSED) 03/19/2026
A64: 6 | B64: Phone number format validation | C64: 1. Enter invalid phone number format 2. Save supplier | D64: System shows phone number validation error | E64: Accepts phone number format with alphabetical characters | F64: Passed | G64: (PASSED) 03/17/2026
A65: 7 | B65: Add supplier with optional fields | C65: 1. Fill Name and Category 2. Leave optional fields empty 3. Save | D65: Supplier is successfully created | F65: Passed
A66: 8 | B66: Add contact person | C66: 1. Click Add Supplier 2. Click Add Contact 3. Enter contact details 4. Save supplier | D66: Contact person is successfully added to supplier | F66: Passed
A67: 9 | B67: Contact Email format validation | C67: 1. Enter invalid email format 2. Save supplier | D67: System shows email validation error | E67: Accepts email format with no domain extension (e.g. test@example) | F67: Passed | G67: (PASSED) 03/19/2026
A68: 10 | B68: Contact Phone number format validation | C68: 1. Enter invalid phone number format 2. Save supplier | D68: System shows phone number validation error | E68: Accepts phone number format with alphabetical characters | F68: Passed | G68: (PASSED) 03/17/2026
A69: 11 | B69: View supplier details | C69: 1. Select existing supplier 2. Click View | D69: Supplier information is displayed correctly | F69: Passed
A70: 12 | B70: Edit supplier | C70: 1. Select supplier 2. Click Edit 3. Modify information 4. Save | D70: Supplier information is updated successfully | F70: Passed
A71: 13 | B71: Delete supplier | C71: 1. Select supplier 2. Click Delete 3. Confirm deletion | D71: Supplier is removed from the list | F71: Passed
A72: 14 | B72: Export suppliers list | C72: 1. Click Export button | D72: Supplier data file downloads successfully | F72: Passed
A73: 15 | B73: Export suppliers list with filter | C73: 1. Select category filter 2. Click Export button | D73: Supplier data file downloads successfully | E73: Exports all data even with filters | F73: Failed
A74: 16 | B74: Import suppliers list | C74: 1. Click Import 2. Upload valid file 3. Submit | D74: Suppliers are imported successfully into the system | E74: System shows error: "Failed to parse file" | F74: Failed
A75: 17 | B75: Search supplier | C75: 1. Enter supplier name in Search field | D75: Matching suppliers are displayed | F75: Passed
A76: 18 | B76: Search non-existing supplier | C76: 1. Enter invalid keyword | D76: System displays no results | F76: Passed
A77: 19 | B77: Filter suppliers by category | C77: 1. Select category filter | D77: Only suppliers belonging to selected category are displayed | F77: Passed
A78: 20 | B78: Pagination 10/25/50/100 | C78: 1. Navigate to Wedding Suppliers 2. Select 10 records per page 3. Verify displayed results 4. Select 25, 50, 100 sequentially | D78: System correctly updates displayed supplier records according to selected pagination | F78: Passed
A79: 21 | B79: Add supplier category | C79: 1. Navigate to Manage Categories 2. Enter Category Name 3. Click Add | D79: Category is successfully added | F79: Passed
A80: 22 | B80: Edit supplier category | C80: 1. Select category 2. Click Edit 3. Update name 4. Save | D80: Category is updated successfully | F80: Passed
A81: 23 | B81: Delete supplier category | C81: 1. Select category2. Click Delete | D81: Category is removed successfully | F81: Passed
A82: 24 | B82: Prevent deletion if category in use | C82: 1. Try deleting category assigned to supplier | D82: System prevents deletion or prompts warning | E82: Deletion of category also deletes linked wedding supplier record | F82: Passed | G82: (PASSED) 03/24/2026
A83: Media
A84: 1 | B84: Media Library page loads | C84: 1. Login as Super Admin 2. Navigate to Media Library | D84: Media Library page loads successfully | F84: Passed
A85: 2 | B85: Upload media file | C85: 1. Click Upload Media 2. Select valid file 3. Upload | D85: File uploads successfully and appears in Media Library | F85: Passed
A86: 3 | B86: Upload multiple media files | C86: 1. Upload multiple files simultaneously | D86: All selected files upload successfully | F86: Passed
A87: 4 | B87: Upload unsupported file format | C87: 1. Upload invalid file type | D87: System displays file format validation error | F87: Passed
A88: 5 | B88: Upload file exceeding size limit | C88: 1. Upload file exceeding system limit | D88: System prevents upload and displays error message | F88: Passed
A89: 6 | B89: Search media file | C89: 1. Enter file name in Search field | D89: Matching media files are displayed | F89: Passed
A90: 7 | B90: Search non-existing media file | C90: 1. Enter invalid keyword | D90: System displays no results | F90: Passed
A91: Plans- Plan
A92: 1 | B92: Plans page loads | C92: 1. Navigate to Plans module | D92: Plans page loads successfully | F92: Passed
A93: 2 | B93: Monthly / Yearly toggle | C93: 1. Switch Monthly/Yearly toggle | D93: Plans display correct pricing based on toggle selection | F93: Passed
A94: 3 | B94: Add plan with valid data | C94: 1. Click Add Plan2. Fill required fields3. Save | D94: Plan is successfully created | F94: Passed
A95: 4 | B95: Add plan with missing required fields | C95: 1. Leave required fields blank2. Click Save | D95: System displays validation errors | F95: Passed
A96: 5 | B96: Add currency to plan | C96: 1. Click Add Currency 2. Select currency from dropdown 3. Enter monthly and yearly price | D96: Currency pricing is successfully added to plan | F96: Passed
A97: 6 | B97: Enable Branding toggle | C97: 1. Enable Branding toggle while creating plan | D97: Branding feature is enabled for the plan | F97: Passed
A98: 7 | B98: AI Integration toggle | C98: 1. Enable AI Integration toggle | D98: AI features become enabled for the plan | F98: Passed
A99: 8 | B99: Enable Trial toggle | C99: 1. Enable Trial toggle2. Enter trial days | D99: Plan trial configuration saved successfully | F99: Passed
A100: 9 | B100: Set default plan | C100: 1. Enable Default Plan toggle | D100: Selected plan becomes system default | F100: Passed
A101: 10 | B101: Activate/Deactivate plan | C101: 1. Toggle Active switch | D101: Plan status updates accordingly | F101: Passed
A102: 11 | B102: Edit plan | C102: 1. Select plan 2. Click Edit 3. Modify details 4. Save | D102: Plan details update successfully | F102: Passed
A103: 12 | B103: Delete plan | C103: 1. Select plan 2. Click Delete 3. Confirm | D103: Plan is removed from system | F103: Passed
A104: 13 | B104: Prevent deletion of active subscribed plan | C104: 1. Try deleting plan used by active subscription | D104: System prevents deletion or displays warning | F104: Passed
A105: Plans - Plan Request
A106: 1 | B106: View plan requests | C106: 1. Navigate to Plan Requests | D106: All plan requests are displayed | F106: Passed
A107: 2 | B107: Approve plan request | C107: 1. Select pending request2. Click Approve | D107: Request status changes to Approved | F107: Passed
...
